ImageGoNord/GoNord.py
ImageGoNord/GoNord_test.py
ImageGoNord/__init__.py
ImageGoNord/models/__init__.py
ImageGoNord/models/PaletteNet/__init__.py
ImageGoNord/palettes/__init__.py
ImageGoNord/palettes/Nord/Aurora.txt
ImageGoNord/palettes/Nord/Frost.txt
ImageGoNord/palettes/Nord/PolarNight.txt
ImageGoNord/palettes/Nord/SnowStorm.txt
ImageGoNord/palettes/Nord/__init__.py
ImageGoNord/utility/ConvertUtility.py
ImageGoNord/utility/__init__.py
ImageGoNord/utility/model.py
ImageGoNord/utility/palette_loader.py
ImageGoNord/utility/quantize.py
image_go_nord-1.2.0.dist-info/LICENSE
image_go_nord-1.2.0.dist-info/METADATA
image_go_nord-1.2.0.dist-info/WHEEL
image_go_nord-1.2.0.dist-info/top_level.txt
image_go_nord-1.2.0.dist-info/RECORD
