Metadata-Version: 2.1
Name: image-go-nord
Version: 1.2.0
Summary: A tool to convert any RGB image or video to any theme or color palette input by the user
Home-page: https://github.com/Schrodinger-Hat/ImageGoNord-pip
Author: Schrodinger Hat
Author-email: schrodinger.hat.show@gmail.com
License: AGPL-3.0
Download-URL: https://github.com/Schrodinger-Hat/ImageGoNord-pip/releases
Project-URL: Homepage, https://ign.schrodinger-hat.it
Project-URL: Source, https://github.com/Schrodinger-Hat/ImageGoNord-pip
Project-URL: Bug Reports, https://github.com/Schrodinger-Hat/ImageGoNord-pip/issues
Keywords: nordtheme,pillow,image,conversion,rgb,color-scheme,color-palette,linux-rice,gruvbox,catpuccin
Platform: UNKNOWN
Classifier: Development Status :: 5 - Production/Stable
Classifier: Intended Audience :: Developers
Classifier: Topic :: Software Development :: Build Tools
Classifier: License :: OSI Approved :: GNU Affero General Public License v3 or later (AGPLv3+)
Classifier: Programming Language :: Python :: 3
Classifier: Programming Language :: Python :: 3.7
Requires-Python: >=3.5
License-File: LICENSE
Requires-Dist: Pillow
Requires-Dist: ffmpeg-python
Requires-Dist: numpy
Requires-Dist: requests
Provides-Extra: ai
Requires-Dist: torch; extra == "ai"
Requires-Dist: scikit-image; extra == "ai"
Requires-Dist: torchvision; extra == "ai"
